{
	"Home": "Rumah",
	"About Us": "Tentang kami",
	"Buy": "Membeli",
	"Rent": "Menyewa",
	"Find Agent": "Cari Agen",
	"LOG IN": "GABUNG",
	"SIGN UP": "DAFTAR",
	"Profile": "Profil",
	"My Properties": "Properti Saya",
	"Transactions": "Transaksi",
	"Membership": "Keanggotaan",
	"Notifications": "Pemberitahuan",
	"Property as Favorite": "Properti sebagai Favorit",
	"Logout": "Keluar",
	"Transaction": "Transaksi",
	"Find a home you'll love": "Temukan rumah yang Anda sukai",
	"SEARCH": "CARI",
	"Only with us": "Hanya dengan kami",
	"only with us para": " Lorem Ipsum hanyalah teks tiruan dari industri percetakan dan penyusunan huruf. Lorem Ipsum telah menjadi teks dummy Standar industri sejak tahun 1500-an, ketika seorang pencetak yang tidak dikenal mengambil sebuah dapur.",
	"List your properties": "Daftar properti Anda",
	"Feature your properties": "Tampilkan properti Anda",
	"Receive direct enquiries": "Terima pertanyaan langsung",
	"Property Data analysis": "Analisis Data Properti",
	"Free Registration": "Pendaftaran gratis",
	"Search all agency properties on 1 site": "Cari semua properti agensi di 1 situs",
	"Easily search large database": "Cari database besar dengan mudah",
	"Shortlist your favorite properties": "Daftar pendek properti favorit Anda",
	"REGISTER AS USER": "DAFTAR SEBAGAI PENGGUNA",
	"We've unlocked Top cities": "Kami telah membuka kunci kota-kota teratas",
	"Bali": "Bali",
	"Denpasar": "Denpasar",
	"Pura Tanah Lot": "Pura Tanah Lot",
	"Pura Ulun Danu Bratan": "Pura Ulun Danu Bratan",
	"Seminyak Shopping": "Belanja Seminyak",
	"The Nusa Islands": "Kepulauan Nusa",
	"Kuta Beach": "Pantai Kuta",
	"Business Bay": "Teluk Bisnis",
	"Terms & Conditions": "Syarat & Ketentuan",
	"Privacy Policy": "Kebijakan pribadi",
	"All rights reserved": "Seluruh hak cipta",
	"Properties for sale in Bali": "Properti Dijual di Bali",
	"Caregiver not found.": "Pengasuh tidak ditemukan.",
	"VIEW PROFILE": "TAMPILKAN PROFIL",
	"Change Password": "Ganti kata sandi",
	"First Name": "Nama depan",
	"Last Name": "Nama keluarga",
	"Email Address": "Alamat email",
	"Contact Number": "Nomor kontak",
	"Date of Birth": "Tanggal lahir",
	"Address": "Alamat",
	"Gender": "Jenis kelamin",
	"Male": "Pria",
	"Female": "Perempuan",
	"Other": "Lainnya",
	"ORN # of the Agency": "ORN # Agensi",
	"About Me": "Tentang saya",
	"SUBMIT": "KIRIMKAN",
	"Only type A-Za-z character": "Hanya ketik karakter A-Za-z",
	"First name is required": "Nama depan wajib diisi",
	"Last name is required": "Nama belakang wajib diisi",
	"Contact number is required": "Nomor kontak diperlukan",
	"Location is required": "Lokasi diperlukan",
	"ORN # of the agency is required": "ORN # agensi diperlukan",
	"Change Profile Photo": "Ubah Foto Profil",
	"Current Password*": "Kata sandi saat ini*",
	"Old password is required": "Kata sandi lama diperlukan",
	"New Password*": "Kata sandi baru*",
	"New Password is required": "Kata sandi baru diperlukan",
	"New password must be at least 6 characters": "Kata sandi baru harus minimal 6 karakter",
	"Confirm New Password*": "Konfirmasi password baru*",
	"Confirm password is required": "Konfirmasi kata sandi diperlukan",
	"Confirm password must be at least 6 characters": "Konfirmasi kata sandi harus minimal 6 karakter",
	"Submit": "Kirim",
	"My Property": "Properti Saya",
	"Sale Properties": "Dijual Properti",
	"ADD PROPERTY": "TAMBAHKAN PROPERTI",
	"Rent Properties": "Sewa Properti",
	"Add Property": "Tambahkan Properti",
	"Name of Property": "Nama Properti",
	"Accommodation name is required": "Nama akomodasi wajib diisi",
	"Property Type": "jenis properti",
	"Property type is required": "Jenis properti wajib diisi",
	"No. of Bedrooms": "Jumlah Kamar Tidur",
	"No. of Bathroom": "Jumlah Kamar Mandi",
	"Property Size": "Ukuran Properti",
	"Extra Chair": "Kursi Ekstra",
	"Team Meeting": "Rapat Tim",
	"TV Set": "TV Set",
	"- Please Select -": "- Silahkan pilih -",
	"Yes": "Ya",
	"No": "Tidak",
	"Property size is required": "Ukuran properti diperlukan",
	"No. of bathroom is required": "Jumlah kamar mandi yang diperlukan",
	"No. of bedrooms is required": "Jumlah kamar tidur diperlukan",
	"Location": "Lokasi",
	"Frequency": "Frekuensi",
	"Frequency is required": "Frekuensi diperlukan",
	"Price": "Harga",
	"Sale -Freehold": "Dijual -Hak Milik",
	"Sale -Leasehold": "Dijual -Leasehold",
	"No. Of Years": "Jumlah Tahun",
	"Amenities": "Fasilitas",
	"Amenities is required": "Fasilitas diperlukan",
	"Images is required": "Gambar diperlukan",
	"Quick video is required": "Video cepat diperlukan",
	"About is required": "Tentang diperlukan",
	"SUBMIT FOR VERIFICATION": "KIRIM UNTUK VERIFIKASI",
	"Drop documents here to upload or": "Letakkan dokumen di sini untuk mengunggah atau",
	"Choose File": "Pilih File",
	"Your browser does not support the video tag.": "Browser Anda tidak mendukung tag video.",
	"Transactions not found": "Transaksi tidak ditemukan",
	"Transaction History": "sejarah transaksi",
	"ID": "PENGENAL",
	"Amount": "Jumlah",
	"Transaction Date": " tanggal transaksi ",
	"Transaction ID": "ID transaksi",
	"Notification not found": "Notifikasi tidak ditemukan",
	"Login": "Gabung",
	"Sign Up": "Daftar",
	"Email Address*": "Alamat email*",
	"Email address is required": "Alamat email diperlukan",
	"Email address not valid": "Alamat email tidak valid",
	"Password*": "Kata sandi*",
	"Password is required": "katakunci dibutuhkan",
	"Password must be at least 6 characters": "Kata sandi harus minimal 6 karakter",
	"Remember me": "Ingat saya",
	"Forgot Password?": "Tidak ingat kata sandi?",
	"Don't have an account? ": "Tidak punya akun? ",
	"Here.": "Di Sini.",
	"Sign up": "Daftar",
	"Don't have an account?": "Tidak punya akun?",
	"Forgot Password": "Tidak ingat kata sandi",
	"We'll help you reset it and get back on track.": "Kami akan membantu Anda mengatur ulang dan kembali ke jalur semula.",
	"Back to Log in": "Kembali untuk masuk",
	"Back to Login": "Kembali untuk masuk",
	"Register as User": "Daftar sebagai Pengguna",
	"Register as Client": "Daftar sebagai Klien",
	"Recaptcha is required": " Recaptcha diperlukan",
	"Confirm Password*": "Konfirmasi sandi*",
	"I accept the terms and conditions of": "Saya menerima syarat dan ketentuan dari",
	"Bali Property Search": " Pencarian Properti Bali",
	"Terms and conditions is required": "Syarat dan ketentuan diperlukan",
	"Already have an Account? Please": "Sudah memiliki akun? Silahkan",
	"Email already": "Sudah email",
	"exists": "ada",
	" Register as Client": "Daftar sebagai Klien",
	"First Name*": "Nama depan*",
	"Last Name*": "Nama keluarga*",
	"New properties for": "Properti baru untuk",
	"rent": "menyewa",
	"Rent property not found": "Sewa properti tidak ditemukan",
	"Sale property not found": "Dijual properti tidak ditemukan",
	"Contact": "Kontak",
	"Date": "Tanggal",
	"Date is required": "Tanggal wajib diisi",
	"Comment": "Komentar",
	"Comment is required": "Komentar diperlukan",
	"Email": "Surel",
	"Back to search results": "kembali ke hasil pencarian",
	"Property Type:": "Jenis properti:",
	"Property size:": "Ukuran properti:",
	"Bedrooms:": "Kamar tidur:",
	"Bathrooms:": "Kamar mandi:",
	"Creek Gate": "Gerbang Sungai",
	"Amenities not found": "Fasilitas tidak ditemukan",
	"Property Description": "Deskripsi properti",
	"VIEW CONTACTS": "LIHAT KONTAK",
	"VERIFIED": "DIVERIFIKASI",
	"Bali Property Search has verified the accuracy and authenticity of this listing.": "Bali Property Search telah memverifikasi keakuratan dan keaslian listing ini.",
	"Save to Shortlist": "Simpan ke Daftar Pendek",
	"About Agent": "Tentang Agen",
	"Property Consultant at Allsopp & Allsopp": "Konsultan Properti di Allsopp & Allsopp",
	"- Business Bay...": "- Teluk Bisnis...",
	"ORN #:": "ORN #:",
	"#36247": "#36247",
	"CONTACT SELLER": "HUBUNGI PENJUAL",
	"Sale Favorite Properties": "Jual Properti Favorit",
	"Rent Favorite Properties": "Sewa Properti Favorit",
	"Your Wishlist is Empty": "Daftar keinginan anda kosong",
	"sale": "penjualan",
	"Page not available admin please add page to admin": "Halaman tidak tersedia admin silakan tambahkan halaman ke admin",
	"SHOW": "MENUNJUKKAN",
	"PHOTOS": "FOTO",
	"WATCH VIDEO TOUR": "WATCH VIDEO TOUR",
	"Property not found": "Properti tidak ditemukan",
	"Load More": "Muat lebih banyak",
	"All Property": "Semua Properti",
	"Error Summary:": "Ringkasan Kesalahan:",
	"Dashboard": "Dasbor",
	"Total Booking": "Jumlah Pemesanan",
	"Completed Booking": "Pemesanan Selesai",
	"In-Person Viewing Request": "Permintaan Melihat Langsung",
	"Total Sells": "Total Penjualan",
	"Requests": "Permintaan",
	"Property description is required": "Deskripsi properti wajib diisi",
	"Add to Favourite": "Tambahkan ke Favorit",
	"DETAILS": " RINCIAN",
	"Remove from favorite": "Hapus dari favorit",
	"Appointments": "Janji temu",
	"Declined": "Ditolak",
	"Completed": "Lengkap",
	"Id": "Indo",
	"Service Name": "Nama layanan",
	"Client Name": "Nama Klien",
	"Time": "Waktu",
	"Status": "Status",
	"Action": "Tindakan",
	"In-Person Viewing not found": "Tampilan Langsung tidak ditemukan"
}